AO3/__init__.py
AO3/chapters.py
AO3/comments.py
AO3/common.py
AO3/extra.py
AO3/requester.py
AO3/search.py
AO3/series.py
AO3/session.py
AO3/threadable.py
AO3/users.py
AO3/utils.py
AO3/works.py
ao3_api-2.3.1.dist-info/LICENSE
ao3_api-2.3.1.dist-info/METADATA
ao3_api-2.3.1.dist-info/WHEEL
ao3_api-2.3.1.dist-info/top_level.txt
ao3_api-2.3.1.dist-info/RECORD
