Metadata-Version: 2.2
Name: ao3-api
Version: 2.3.1
Summary: An unofficial AO3 (archiveofourown.org) API
Author: Wendy
Project-URL: Homepage, https://github.com/wendytg/ao3_api
Project-URL: Issues, https://github.com/wendytg/ao3_api/issues
Project-URL: Documentation, https://ao3-api.readthedocs.io/
Keywords: ao3,fanfiction,Archive of Our Own
Classifier: Programming Language :: Python :: 3
Classifier: License :: OSI Approved :: MIT License
Classifier: Operating System :: OS Independent
Requires-Python: >=3.8
License-File: LICENSE
Requires-Dist: BeautifulSoup4
Requires-Dist: lxml
Requires-Dist: requests
